<annotation>
	<folder>Amanita</folder>
	<filename>611_ZVPMBfF9UXo.jpg</filename>
	<path>C:\Users\tah05\Desktop\Amanita\611_ZVPMBfF9UXo.jpg</path>
	<source>
		<database>Unknown</database>
	</source>
	<size>
		<width>800</width>
		<height>478</height>
		<depth>3</depth>
	</size>
	<segmented>0</segmented>
	<object>
		<name>me</name>
		<pose>Unspecified</pose>
		<truncated>0</truncated>
		<difficult>0</difficult>
		<bndbox>
			<xmin>8</xmin>
			<ymin>95</ymin>
			<xmax>278</xmax>
			<ymax>385</ymax>
		</bndbox>
	</object>
	<object>
		<name>me</name>
		<pose>Unspecified</pose>
		<truncated>0</truncated>
		<difficult>0</difficult>
		<bndbox>
			<xmin>206</xmin>
			<ymin>134</ymin>
			<xmax>460</xmax>
			<ymax>361</ymax>
		</bndbox>
	</object>
	<object>
		<name>me</name>
		<pose>Unspecified</pose>
		<truncated>0</truncated>
		<difficult>0</difficult>
		<bndbox>
			<xmin>431</xmin>
			<ymin>118</ymin>
			<xmax>722</xmax>
			<ymax>332</ymax>
		</bndbox>
	</object>
	<object>
		<name>me</name>
		<pose>Unspecified</pose>
		<truncated>0</truncated>
		<difficult>0</difficult>
		<bndbox>
			<xmin>270</xmin>
			<ymin>73</ymin>
			<xmax>528</xmax>
			<ymax>199</ymax>
		</bndbox>
	</object>
	<object>
		<name>me</name>
		<pose>Unspecified</pose>
		<truncated>0</truncated>
		<difficult>0</difficult>
		<bndbox>
			<xmin>591</xmin>
			<ymin>194</ymin>
			<xmax>791</xmax>
			<ymax>384</ymax>
		</bndbox>
	</object>
</annotation>
